ovos_ww_plugin_openwakeword/__init__.py
ovos_ww_plugin_openwakeword/version.py
ovos_ww_plugin_openwakeword-0.4.1.dist-info/LICENSE
ovos_ww_plugin_openwakeword-0.4.1.dist-info/METADATA
ovos_ww_plugin_openwakeword-0.4.1.dist-info/WHEEL
ovos_ww_plugin_openwakeword-0.4.1.dist-info/entry_points.txt
ovos_ww_plugin_openwakeword-0.4.1.dist-info/top_level.txt
ovos_ww_plugin_openwakeword-0.4.1.dist-info/RECORD
