Metadata-Version: 2.1
Name: ovos-ww-plugin-openwakeword
Version: 0.4.1
Summary: A wakeword plugin for OpenVoiceOS for the openWakeWord library
Home-page: https://github.com/OpenVoiceOS/ovos-ww-plugin-openwakeword
Author: dscripka
Author-email: david.scripka@gmail.com
License: Apache-2.0
Keywords: mycroft ovos plugin
Platform: UNKNOWN
Requires-Dist: openwakeword <1,>=0.5.0
